dryable/__init__.py
dryable-1.2.0.dist-info/LICENSE
dryable-1.2.0.dist-info/METADATA
dryable-1.2.0.dist-info/WHEEL
dryable-1.2.0.dist-info/top_level.txt
dryable-1.2.0.dist-info/RECORD
