Metadata-Version: 2.1
Name: dryable
Version: 1.2.0
Summary: provide --dry-run functionality for your application
Home-page: https://github.com/haarcuba/dryable
Author: Yoav Kleinberger
Author-email: haarcuba@gmail.com
Keywords: subprocess
Classifier: Programming Language :: Python :: 3
Classifier: Intended Audience :: Developers
Classifier: License :: OSI Approved :: MIT License
Classifier: Operating System :: OS Independent
License-File: LICENSE
Provides-Extra: testing
Requires-Dist: pytest ; extra == 'testing'
